CHANGES.rst
CONTRIBUTORS.rst
MANIFEST.in
README.rst
setup.py
docs/Makefile
docs/__init__.py
docs/__init__.pyc
docs/conf.py
docs/index.rst
docs/requirements.txt
docs/_build/doctrees/environment.pickle
docs/_build/doctrees/index.doctree
docs/_build/doctrees/api/downloader.doctree
docs/_build/doctrees/api/downloader.downloader.doctree
docs/_build/doctrees/api/downloader.structures.doctree
docs/_build/doctrees/api/downloader.structures.requests.doctree
docs/_build/doctrees/api/downloader.structures.responses.doctree
docs/_build/doctrees/api/modules.doctree
docs/_build/html/.buildinfo
docs/_build/html/genindex.html
docs/_build/html/index.html
docs/_build/html/objects.inv
docs/_build/html/py-modindex.html
docs/_build/html/search.html
docs/_build/html/searchindex.js
docs/_build/html/_modules/downloader.html
docs/_build/html/_modules/index.html
docs/_build/html/_modules/downloader/downloader.html
docs/_build/html/_modules/downloader/structures/requests.html
docs/_build/html/_modules/downloader/structures/responses.html
docs/_build/html/_sources/index.txt
docs/_build/html/_sources/api/downloader.downloader.txt
docs/_build/html/_sources/api/downloader.structures.requests.txt
docs/_build/html/_sources/api/downloader.structures.responses.txt
docs/_build/html/_sources/api/downloader.structures.txt
docs/_build/html/_sources/api/downloader.txt
docs/_build/html/_sources/api/modules.txt
docs/_build/html/_static/ajax-loader.gif
docs/_build/html/_static/basic.css
docs/_build/html/_static/comment-bright.png
docs/_build/html/_static/comment-close.png
docs/_build/html/_static/comment.png
docs/_build/html/_static/default.css
docs/_build/html/_static/doctools.js
docs/_build/html/_static/down-pressed.png
docs/_build/html/_static/down.png
docs/_build/html/_static/file.png
docs/_build/html/_static/jquery.js
docs/_build/html/_static/minus.png
docs/_build/html/_static/plus.png
docs/_build/html/_static/pygments.css
docs/_build/html/_static/searchtools.js
docs/_build/html/_static/sidebar.js
src/edeposit.amqp.downloader.egg-info/PKG-INFO
src/edeposit.amqp.downloader.egg-info/SOURCES.txt
src/edeposit.amqp.downloader.egg-info/dependency_links.txt
src/edeposit.amqp.downloader.egg-info/namespace_packages.txt
src/edeposit.amqp.downloader.egg-info/not-zip-safe
src/edeposit.amqp.downloader.egg-info/requires.txt
src/edeposit.amqp.downloader.egg-info/top_level.txt
