Metadata-Version: 1.1
Name: edeposit.amqp.downloader
Version: 0.3.1
Summary: E-Deposit's AMQP bindings to download workers.
Home-page: https://github.com/edeposit/edeposit.amqp.downloader/
Author: Edeposit team
Author-email: edeposit@email.cz
License: GPL2+
Platform: UNKNOWN
Classifier: Programming Language :: Python :: 2.7
Classifier: License :: OSI Approved :: GNU General Public License v2 or later (GPLv2+)
Classifier: Topic :: Software Development :: Libraries :: Python Modules
